dataset_tools/.gitignore
dataset_tools/.python-version
dataset_tools/__init__.py
dataset_tools/__main__.py
dataset_tools/access_disk.py
dataset_tools/background_operations.py
dataset_tools/civitai_api.py
dataset_tools/cli_parse.py
dataset_tools/comfyui_node_dictionary.json
dataset_tools/correct_types.py
dataset_tools/crypto_secrets.py
dataset_tools/dispatcher.py
dataset_tools/display_formatter.py
dataset_tools/event_handlers.py
dataset_tools/file_operations.py
dataset_tools/logger.py
dataset_tools/main.py
dataset_tools/metadata_parser.py
dataset_tools/model_tool.py
dataset_tools/numpy_scorer.py
dataset_tools/rule_evaluator.py
dataset_tools/secrets.json.example
dataset_tools/secrets_config.py
dataset_tools/ui_layout.py
dataset_tools/widgets.py
dataset_tools/config/rules.toml
dataset_tools/file_readers/__init__.py
dataset_tools/file_readers/image_metadata_reader.py
dataset_tools/file_readers/schema_file_reader.py
dataset_tools/file_readers/text_file_reader.py
"dataset_tools/fonts/DMSans-Italic-VariableFont_opsz,wght.ttf"
"dataset_tools/fonts/DMSans-VariableFont_opsz,wght.ttf"
dataset_tools/fonts/Dongle-Bold.ttf
dataset_tools/fonts/Dongle-Light.ttf
dataset_tools/fonts/Dongle-Regular.ttf
dataset_tools/fonts/DoppioOne-Regular.ttf
"dataset_tools/fonts/IBMPlexSans-Italic-VariableFont_wdth,wght.ttf"
"dataset_tools/fonts/IBMPlexSans-VariableFont_wdth,wght.ttf"
"dataset_tools/fonts/Inter-Italic-VariableFont_opsz,wght.ttf"
"dataset_tools/fonts/Inter-VariableFont_opsz,wght.ttf"
dataset_tools/fonts/JetBrainsMono-Bold.ttf
dataset_tools/fonts/JetBrainsMono-Regular.ttf
dataset_tools/fonts/Jura-VariableFont_wght.ttf
dataset_tools/fonts/KosugiMaru-Regular.ttf
dataset_tools/fonts/LICENSE.txt
dataset_tools/fonts/Mandali-Regular.ttf
dataset_tools/fonts/Nunito-Italic-VariableFont_wght.ttf
dataset_tools/fonts/Nunito-VariableFont_wght.ttf
dataset_tools/fonts/OFL.txt
"dataset_tools/fonts/OpenSans-Italic-VariableFont_wdth,wght.ttf"
"dataset_tools/fonts/OpenSans-VariableFont_wdth,wght.ttf"
kn_dataset_tools-0.70.2.dev0.dist-info/licenses/LICENSE
kn_dataset_tools-0.70.2.dev0.dist-info/licenses/NOTICE.md
kn_dataset_tools-0.70.2.dev0.dist-info/METADATA
kn_dataset_tools-0.70.2.dev0.dist-info/WHEEL
kn_dataset_tools-0.70.2.dev0.dist-info/entry_points.txt
kn_dataset_tools-0.70.2.dev0.dist-info/top_level.txt
kn_dataset_tools-0.70.2.dev0.dist-info/RECORD
