Metadata-Version: 2.4
Name: kn-dataset-tools
Version: 0.70.2.dev0
Summary: A Simple Viewer for EXIF and AI Metadata.
Author-email: Ktiseos Nyx <Dataset-Tools@noreply.github.com>
License-Expression: GPL-3.0-or-later
Project-URL: source, https://github.com/Ktiseos-Nyx/Dataset-Tools
Keywords: training,text,images,AI,editing,dataset,metadata,generative,art
Classifier: Topic :: Multimedia :: Graphics
Classifier: Topic :: Multimedia :: Graphics :: Viewers
Classifier: Topic :: Text Processing :: General
Classifier: Topic :: Artistic Software
Classifier: Topic :: Scientific/Engineering :: Artificial Intelligence
Classifier: Intended Audience :: Other Audience
Classifier: Programming Language :: Python :: 3.10
Classifier: Programming Language :: Python :: 3.11
Classifier: Programming Language :: Python :: 3.12
Classifier: Operating System :: OS Independent
Classifier: Environment :: X11 Applications :: Qt
Requires-Python: >=3.10
License-File: LICENSE
License-File: NOTICE.md
Requires-Dist: rich
Requires-Dist: pydantic
Requires-Dist: pydantic-core
Requires-Dist: pillow
Requires-Dist: PyQt6
Requires-Dist: toml
Requires-Dist: typing-extensions
Requires-Dist: pyexiv2
Requires-Dist: pypng
Requires-Dist: cryptography
Requires-Dist: exif
Requires-Dist: numpy
Requires-Dist: piexif
Requires-Dist: defusedxml
Requires-Dist: requests
Requires-Dist: jsonpath-ng
Provides-Extra: dev
Requires-Dist: pytest; extra == "dev"
Requires-Dist: mypy; extra == "dev"
Requires-Dist: types-toml; extra == "dev"
Requires-Dist: types-defusedxml; extra == "dev"
Provides-Extra: kn
Requires-Dist: ruff; extra == "kn"
Requires-Dist: pylint; extra == "kn"
Dynamic: license-file
